odoo/addons/license_ocad_mail/LICENSE
odoo/addons/license_ocad_mail/README.rst
odoo/addons/license_ocad_mail/__init__.py
odoo/addons/license_ocad_mail/__manifest__.py
odoo/addons/license_ocad_mail/data/mail_templates.xml
odoo/addons/license_ocad_mail/i18n/de.po
odoo/addons/license_ocad_mail/images/screen.png
odoo/addons/license_ocad_mail/models/__init__.py
odoo/addons/license_ocad_mail/models/sale_order.py
odoo/addons/license_ocad_mail/readme/CONTRIBUTORS.md
odoo/addons/license_ocad_mail/readme/DESCRIPTION.md
odoo/addons/license_ocad_mail/readme/USAGE.md
odoo/addons/license_ocad_mail/static/description/icon.png
odoo/addons/license_ocad_mail/static/description/index.html
odoo/addons/license_ocad_mail/tests/TEST_INSTRUCTIONS.rst
odoo/addons/license_ocad_mail/views/sale_order.xml
odoo_addon_license_ocad_mail-18.0.1.0.0.dist-info/METADATA
odoo_addon_license_ocad_mail-18.0.1.0.0.dist-info/WHEEL
odoo_addon_license_ocad_mail-18.0.1.0.0.dist-info/top_level.txt
odoo_addon_license_ocad_mail-18.0.1.0.0.dist-info/RECORD
